typeforce/__init__.py
typeforce/__main__.py
typeforce/_cli.py
typeforce/_constants.py
typeforce/_core.py
typeforce/_script_inspect.py
typeforce/_script_sites.py
typeforce-0.2.1.dist-info/LICENSE
typeforce-0.2.1.dist-info/WHEEL
typeforce-0.2.1.dist-info/METADATA
typeforce-0.2.1.dist-info/RECORD
