Metadata-Version: 2.1
Name: typeforce
Version: 0.2.1
Summary: CLI tool to propagate py.typed into third-party libraries.
Home-page: https://github.com/orsinium-labs/typeforce
License: MIT
Keywords: mypy,typing
Author: Gram
Author-email: gram@orsinium.dev
Requires-Python: >=3.6
Classifier: Development Status :: 5 - Production/Stable
Classifier: Environment :: Plugins
Classifier: Intended Audience :: Developers
Classifier: License :: OSI Approved :: MIT License
Classifier: Programming Language :: Python
Classifier: Topic :: Software Development
Classifier: Topic :: Software Development :: Quality Assurance
